probounds/__init__.py
probounds/probounds.py
probounds-0.3.5.dist-info/WHEEL
probounds-0.3.5.dist-info/METADATA
probounds-0.3.5.dist-info/RECORD
