Metadata-Version: 2.3
Name: probounds
Version: 0.3.5
Summary: Probability bounds project
Author: Uriah Finkel
Author-email: Uriah Finkel <ufinkel@gmail.com>
Requires-Dist: numpy>=1.26.0
Requires-Dist: polars>=1.6.0,<2.0.0
Requires-Python: >=3.9
